python_test_video_fp/__init__.py
python_test_video_fp/api.py
python_test_video_fp/client.py
python_test_video_fp/exceptions.py
python_test_video_fp/live_streams.py
python_test_video_fp/media.py
python_test_video_fp/playback_ids.py
python_test_video_fp/signing_keys.py
python_test_video_fp-1.1.0.dist-info/METADATA
python_test_video_fp-1.1.0.dist-info/WHEEL
python_test_video_fp-1.1.0.dist-info/top_level.txt
python_test_video_fp-1.1.0.dist-info/RECORD
