Metadata-Version: 2.1
Name: python_test_video_fp
Version: 1.1.0
Summary: Video SDK for processing
Author: subbaraju
Author-email: subba3295@gmail.com
Classifier: Programming Language :: Python :: 3
Classifier: License :: OSI Approved :: MIT License
Requires-Python: >=3.7
Requires-Dist: requests
